Metadata-Version: 2.1
Name: anticipython
Version: 1.0.3
Summary: Create .ics calendars for upcoming CPython releases 🐍👀
Home-page: https://github.com/brcrista/Anticipython
Author: Brian Cristante
License: UNKNOWN
Platform: UNKNOWN
Classifier: Development Status :: 5 - Production/Stable
Classifier: Intended Audience :: Developers
Classifier: License :: OSI Approved :: MIT License
Classifier: Programming Language :: Python
Requires-Python: >=3.6
